{"v":"5.1.16","fr":60,"ip":0,"op":120,"w":400,"h":300,"nm":"seedsearch-animation","ddd":0,"assets":[{"id":"comp_0","layers":[{"ddd":0,"ind":1,"ty":4,"nm":"glass","sr":1,"ks":{"o":{"a":0,"k":15,"ix":11},"r":{"a":1,"k":[{"i":{"x":[0.8],"y":[1]},"o":{"x":[0.2],"y":[0]},"n":["0p8_1_0p2_0"],"t":0,"s":[-5],"e":[15]},{"i":{"x":[0.8],"y":[1]},"o":{"x":[0.2],"y":[0]},"n":["0p8_1_0p2_0"],"t":30,"s":[15],"e":[-12]},{"i":{"x":[0.8],"y":[1]},"o":{"x":[0.2],"y":[0]},"n":["0p8_1_0p2_0"],"t":60,"s":[-12],"e":[10]},{"i":{"x":[0.8],"y":[1]},"o":{"x":[0.2],"y":[0]},"n":["0p8_1_0p2_0"],"t":90,"s":[10],"e":[-5]},{"t":120}],"ix":10},"p":{"a":1,"k":[{"i":{"x":0.8,"y":1},"o":{"x":0.2,"y":0},"n":"0p8_1_0p2_0","t":0,"s":[844.678,643.457,0],"e":[912.284,711.062,0],"to":[0,0,0],"ti":[0,0,0]},{"i":{"x":0.8,"y":1},"o":{"x":0.2,"y":0},"n":"0p8_1_0p2_0","t":30,"s":[912.284,711.062,0],"e":[865.795,756.602,0],"to":[0,0,0],"ti":[0,0,0]},{"i":{"x":0.8,"y":1},"o":{"x":0.2,"y":0},"n":"0p8_1_0p2_0","t":60,"s":[865.795,756.602,0],"e":[922.842,877.495,0],"to":[0,0,0],"ti":[0,0,0]},{"i":{"x":0.8,"y":1},"o":{"x":0.2,"y":0},"n":"0p8_1_0p2_0","t":90,"s":[922.842,877.495,0],"e":[844.678,643.457,0],"to":[0,0,0],"ti":[0,0,0]},{"t":120}],"ix":2},"a":{"a":0,"k":[319.819,319.821,0],"ix":1},"s":{"a":0,"k":[150,150,100],"ix":6}},"ao":0,"shapes":[{"ty":"gr","it":[{"ind":0,"ty":"sh","ix":1,"ks":{"a":0,"k":{"i":[[46.637,0],[0,46.636],[-46.635,0],[0,-46.636]],"o":[[-46.635,0],[0,-46.636],[46.637,0],[0,46.636]],"v":[[-0.001,84.282],[-84.282,0],[-0.001,-84.282],[84.282,0]],"c":true},"ix":2},"nm":"Path 1","mn":"ADBE Vector Shape - Group","hd":false},{"ty":"fl","c":{"a":0,"k":[0.327512254902,0.774889777688,1,1],"ix":4},"o":{"a":0,"k":100,"ix":5},"r":1,"nm":"Fill 1","mn":"ADBE Vector Graphic - Fill","hd":false},{"ty":"tr","p":{"a":0,"k":[122.152,122.154],"ix":2},"a":{"a":0,"k":[0,0],"ix":1},"s":{"a":0,"k":[100,100],"ix":3},"r":{"a":0,"k":0,"ix":6},"o":{"a":0,"k":100,"ix":7},"sk":{"a":0,"k":0,"ix":4},"sa":{"a":0,"k":0,"ix":5},"nm":"Transform"}],"nm":"Group 1","np":2,"cix":2,"ix":1,"mn":"ADBE Vector Group","hd":false}],"ip":0,"op":240,"st":0,"bm":0},{"ddd":0,"ind":2,"ty":4,"nm":"mask","td":1,"sr":1,"ks":{"o":{"a":0,"k":100,"ix":11},"r":{"a":1,"k":[{"i":{"x":[0.8],"y":[1]},"o":{"x":[0.2],"y":[0]},"n":["0p8_1_0p2_0"],"t":0,"s":[-5],"e":[15]},{"i":{"x":[0.8],"y":[1]},"o":{"x":[0.2],"y":[0]},"n":["0p8_1_0p2_0"],"t":30,"s":[15],"e":[-12]},{"i":{"x":[0.8],"y":[1]},"o":{"x":[0.2],"y":[0]},"n":["0p8_1_0p2_0"],"t":60,"s":[-12],"e":[10]},{"i":{"x":[0.8],"y":[1]},"o":{"x":[0.2],"y":[0]},"n":["0p8_1_0p2_0"],"t":90,"s":[10],"e":[-5]},{"t":120}],"ix":10},"p":{"a":1,"k":[{"i":{"x":0.8,"y":1},"o":{"x":0.2,"y":0},"n":"0p8_1_0p2_0","t":0,"s":[844.678,643.457,0],"e":[912.284,711.062,0],"to":[0,0,0],"ti":[0,0,0]},{"i":{"x":0.8,"y":1},"o":{"x":0.2,"y":0},"n":"0p8_1_0p2_0","t":30,"s":[912.284,711.062,0],"e":[865.795,756.602,0],"to":[0,0,0],"ti":[0,0,0]},{"i":{"x":0.8,"y":1},"o":{"x":0.2,"y":0},"n":"0p8_1_0p2_0","t":60,"s":[865.795,756.602,0],"e":[922.842,877.495,0],"to":[0,0,0],"ti":[0,0,0]},{"i":{"x":0.8,"y":1},"o":{"x":0.2,"y":0},"n":"0p8_1_0p2_0","t":90,"s":[922.842,877.495,0],"e":[844.678,643.457,0],"to":[0,0,0],"ti":[0,0,0]},{"t":120}],"ix":2},"a":{"a":0,"k":[319.819,319.821,0],"ix":1},"s":{"a":0,"k":[150,150,100],"ix":6}},"ao":0,"shapes":[{"ty":"gr","it":[{"ind":0,"ty":"sh","ix":1,"ks":{"a":0,"k":{"i":[[46.637,0],[0,46.636],[-46.635,0],[0,-46.636]],"o":[[-46.635,0],[0,-46.636],[46.637,0],[0,46.636]],"v":[[-0.001,84.282],[-84.282,0],[-0.001,-84.282],[84.282,0]],"c":true},"ix":2},"nm":"Path 1","mn":"ADBE Vector Shape - Group","hd":false},{"ty":"fl","c":{"a":0,"k":[1,1,1,1],"ix":4},"o":{"a":0,"k":100,"ix":5},"r":1,"nm":"Fill 1","mn":"ADBE Vector Graphic - Fill","hd":false},{"ty":"tr","p":{"a":0,"k":[122.152,122.154],"ix":2},"a":{"a":0,"k":[0,0],"ix":1},"s":{"a":0,"k":[100,100],"ix":3},"r":{"a":0,"k":0,"ix":6},"o":{"a":0,"k":100,"ix":7},"sk":{"a":0,"k":0,"ix":4},"sa":{"a":0,"k":0,"ix":5},"nm":"Transform"}],"nm":"Group 1","np":2,"cix":2,"ix":1,"mn":"ADBE Vector Group","hd":false}],"ip":0,"op":240,"st":0,"bm":0},{"ddd":0,"ind":3,"ty":4,"nm":"qr Outlines 2","tt":1,"sr":1,"ks":{"o":{"a":0,"k":100,"ix":11},"r":{"a":0,"k":0,"ix":10},"p":{"a":1,"k":[{"i":{"x":0.7,"y":1},"o":{"x":0.3,"y":0},"n":"0p7_1_0p3_0","t":0,"s":[646.816,511.95,0],"e":[563.049,485.232,0],"to":[-13.9612684249878,-4.45305395126343,0],"ti":[-0.18075053393841,19.5211277008057,0]},{"i":{"x":0.7,"y":1},"o":{"x":0.3,"y":0},"n":"0p7_1_0p3_0","t":30,"s":[563.049,485.232,0],"e":[647.901,394.823,0],"to":[0.18075053393841,-19.5211277008057,0],"ti":[2.29577374458313,13.4929580688477,0]},{"i":{"x":0.7,"y":1},"o":{"x":0.3,"y":0},"n":"0p7_1_0p3_0","t":60,"s":[647.901,394.823,0],"e":[549.274,404.274,0],"to":[-2.29577374458313,-13.4929580688477,0],"ti":[0.18075053393841,-19.5211277008057,0]},{"i":{"x":0.7,"y":1},"o":{"x":0.3,"y":0},"n":"0p7_1_0p3_0","t":90,"s":[549.274,404.274,0],"e":[646.816,511.95,0],"to":[-0.18075053393841,19.5211277008057,0],"ti":[-16.2570419311523,-17.9460124969482,0]},{"t":120}],"ix":2},"a":{"a":0,"k":[162.539,162.538,0],"ix":1},"s":{"a":0,"k":[150,150,100],"ix":6}},"ao":0,"shapes":[{"ty":"gr","it":[{"ind":0,"ty":"sh","ix":1,"ks":{"a":0,"k":{"i":[[0,0],[0,0],[0,0],[0,0]],"o":[[0,0],[0,0],[0,0],[0,0]],"v":[[72.141,-72.122],[108.193,-72.122],[108.193,-108.192],[72.141,-108.192]],"c":true},"ix":2},"nm":"Path 1","mn":"ADBE Vector Shape - Group","hd":false},{"ind":1,"ty":"sh","ix":2,"ks":{"a":0,"k":{"i":[[0,0]],"o":[[0,0]],"v":[[72.141,-108.191]],"c":false},"ix":2},"nm":"Path 2","mn":"ADBE Vector Shape - Group","hd":false},{"ind":2,"ty":"sh","ix":3,"ks":{"a":0,"k":{"i":[[0,0],[0,0],[0,0],[0,0]],"o":[[0,0],[0,0],[0,0],[0,0]],"v":[[72.141,108.192],[108.193,108.192],[108.193,72.122],[72.141,72.122]],"c":true},"ix":2},"nm":"Path 3","mn":"ADBE Vector Shape - Group","hd":false},{"ind":3,"ty":"sh","ix":4,"ks":{"a":0,"k":{"i":[[0,0]],"o":[[0,0]],"v":[[72.141,72.123]],"c":false},"ix":2},"nm":"Path 4","mn":"ADBE Vector Shape - Group","hd":false},{"ind":4,"ty":"sh","ix":5,"ks":{"a":0,"k":{"i":[[0,0],[0,0],[0,0],[0,0]],"o":[[0,0],[0,0],[0,0],[0,0]],"v":[[-108.191,108.192],[-72.122,108.192],[-72.122,72.122],[-108.191,72.122]],"c":true},"ix":2},"nm":"Path 5","mn":"ADBE Vector Shape - Group","hd":false},{"ind":5,"ty":"sh","ix":6,"ks":{"a":0,"k":{"i":[[0,0]],"o":[[0,0]],"v":[[-108.191,72.123]],"c":false},"ix":2},"nm":"Path 6","mn":"ADBE Vector Shape - Group","hd":false},{"ind":6,"ty":"sh","ix":7,"ks":{"a":0,"k":{"i":[[0,0],[0,0],[0,0],[0,0]],"o":[[0,0],[0,0],[0,0],[0,0]],"v":[[-108.191,-72.122],[-72.122,-72.122],[-72.122,-108.192],[-108.191,-108.192]],"c":true},"ix":2},"nm":"Path 7","mn":"ADBE Vector Shape - Group","hd":false},{"ind":7,"ty":"sh","ix":8,"ks":{"a":0,"k":{"i":[[0,0]],"o":[[0,0]],"v":[[-108.191,-108.191]],"c":false},"ix":2},"nm":"Path 8","mn":"ADBE Vector Shape - Group","hd":false},{"ind":8,"ty":"sh","ix":9,"ks":{"a":0,"k":{"i":[[0,0],[0,0],[0,0],[0,0]],"o":[[0,0],[0,0],[0,0],[0,0]],"v":[[72.141,-72.122],[108.193,-72.122],[108.193,-108.192],[72.141,-108.192]],"c":true},"ix":2},"nm":"Path 9","mn":"ADBE Vector Shape - Group","hd":false},{"ind":9,"ty":"sh","ix":10,"ks":{"a":0,"k":{"i":[[0,0]],"o":[[0,0]],"v":[[72.141,-108.191]],"c":false},"ix":2},"nm":"Path 10","mn":"ADBE Vector Shape - Group","hd":false},{"ind":10,"ty":"sh","ix":11,"ks":{"a":0,"k":{"i":[[0,0],[0,0],[0,0],[0,0]],"o":[[0,0],[0,0],[0,0],[0,0]],"v":[[72.141,-72.122],[108.193,-72.122],[108.193,-108.192],[72.141,-108.192]],"c":true},"ix":2},"nm":"Path 11","mn":"ADBE Vector Shape - Group","hd":false},{"ind":11,"ty":"sh","ix":12,"ks":{"a":0,"k":{"i":[[0,0]],"o":[[0,0]],"v":[[72.141,-108.191]],"c":false},"ix":2},"nm":"Path 12","mn":"ADBE Vector Shape - Group","hd":false},{"ind":12,"ty":"sh","ix":13,"ks":{"a":0,"k":{"i":[[0,0],[0,0],[0,0],[0,0]],"o":[[0,0],[0,0],[0,0],[0,0]],"v":[[72.141,-72.122],[108.193,-72.122],[108.193,-108.192],[72.141,-108.192]],"c":true},"ix":2},"nm":"Path 13","mn":"ADBE Vector Shape - Group","hd":false},{"ind":13,"ty":"sh","ix":14,"ks":{"a":0,"k":{"i":[[0,0]],"o":[[0,0]],"v":[[72.141,-108.191]],"c":false},"ix":2},"nm":"Path 14","mn":"ADBE Vector Shape - Group","hd":false},{"ind":14,"ty":"sh","ix":15,"ks":{"a":0,"k":{"i":[[0,0],[0,0],[0,0],[0,0]],"o":[[0,0],[0,0],[0,0],[0,0]],"v":[[72.141,-72.122],[108.193,-72.122],[108.193,-108.192],[72.141,-108.192]],"c":true},"ix":2},"nm":"Path 15","mn":"ADBE Vector Shape - Group","hd":false},{"ind":15,"ty":"sh","ix":16,"ks":{"a":0,"k":{"i":[[0,0],[0,0],[0,0],[0,0],[0,-21.906]],"o":[[0,0],[0,0],[0,0],[21.906,0],[0,0]],"v":[[144.263,-36.07],[36.07,-36.07],[36.07,-144.262],[104.587,-144.262],[144.263,-104.587]],"c":true},"ix":2},"nm":"Path 16","mn":"ADBE Vector Shape - Group","hd":false},{"ind":16,"ty":"sh","ix":17,"ks":{"a":0,"k":{"i":[[31.88,0],[0,0],[0,0],[0,0],[0,0]],"o":[[0,0],[0,0],[0,0],[0,0],[0,-31.861]],"v":[[104.587,-162.288],[18.044,-162.288],[18.044,-18.025],[162.289,-18.025],[162.289,-104.587]],"c":true},"ix":2},"nm":"Path 17","mn":"ADBE Vector Shape - Group","hd":false},{"ind":17,"ty":"sh","ix":18,"ks":{"a":0,"k":{"i":[[0,0],[0,0],[0,0],[0,0]],"o":[[0,0],[0,0],[0,0],[0,0]],"v":[[72.141,-72.122],[108.193,-72.122],[108.193,-108.192],[72.141,-108.192]],"c":true},"ix":2},"nm":"Path 18","mn":"ADBE Vector Shape - Group","hd":false},{"ind":18,"ty":"sh","ix":19,"ks":{"a":0,"k":{"i":[[0,0]],"o":[[0,0]],"v":[[72.141,-108.191]],"c":false},"ix":2},"nm":"Path 19","mn":"ADBE Vector Shape - Group","hd":false},{"ind":19,"ty":"sh","ix":20,"ks":{"a":0,"k":{"i":[[0,0],[0,0],[0,0],[0,0]],"o":[[0,0],[0,0],[0,0],[0,0]],"v":[[72.141,-72.122],[108.193,-72.122],[108.193,-108.192],[72.141,-108.192]],"c":true},"ix":2},"nm":"Path 20","mn":"ADBE Vector Shape - Group","hd":false},{"ind":20,"ty":"sh","ix":21,"ks":{"a":0,"k":{"i":[[0,0]],"o":[[0,0]],"v":[[72.141,-108.191]],"c":false},"ix":2},"nm":"Path 21","mn":"ADBE Vector Shape - Group","hd":false},{"ind":21,"ty":"sh","ix":22,"ks":{"a":0,"k":{"i":[[0,0],[0,0],[0,0],[0,0]],"o":[[0,0],[0,0],[0,0],[0,0]],"v":[[72.141,-72.122],[108.193,-72.122],[108.193,-108.192],[72.141,-108.192]],"c":true},"ix":2},"nm":"Path 22","mn":"ADBE Vector Shape - Group","hd":false},{"ind":22,"ty":"sh","ix":23,"ks":{"a":0,"k":{"i":[[0,0]],"o":[[0,0]],"v":[[72.141,-108.191]],"c":false},"ix":2},"nm":"Path 23","mn":"ADBE Vector Shape - Group","hd":false},{"ind":23,"ty":"sh","ix":24,"ks":{"a":0,"k":{"i":[[0,0],[0,0],[0,0],[0,0]],"o":[[0,0],[0,0],[0,0],[0,0]],"v":[[72.141,-72.122],[108.193,-72.122],[108.193,-108.192],[72.141,-108.192]],"c":true},"ix":2},"nm":"Path 24","mn":"ADBE Vector Shape - Group","hd":false},{"ind":24,"ty":"sh","ix":25,"ks":{"a":0,"k":{"i":[[0,0]],"o":[[0,0]],"v":[[72.141,-108.191]],"c":false},"ix":2},"nm":"Path 25","mn":"ADBE Vector Shape - Group","hd":false},{"ind":25,"ty":"sh","ix":26,"ks":{"a":0,"k":{"i":[[0,0],[0,0],[0,0],[0,0]],"o":[[0,0],[0,0],[0,0],[0,0]],"v":[[72.141,108.192],[108.193,108.192],[108.193,72.122],[72.141,72.122]],"c":true},"ix":2},"nm":"Path 26","mn":"ADBE Vector Shape - Group","hd":false},{"ind":26,"ty":"sh","ix":27,"ks":{"a":0,"k":{"i":[[0,0]],"o":[[0,0]],"v":[[72.141,72.123]],"c":false},"ix":2},"nm":"Path 27","mn":"ADBE Vector Shape - Group","hd":false},{"ind":27,"ty":"sh","ix":28,"ks":{"a":0,"k":{"i":[[0,0],[0,0],[0,0],[0,0]],"o":[[0,0],[0,0],[0,0],[0,0]],"v":[[-108.191,108.192],[-72.122,108.192],[-72.122,72.122],[-108.191,72.122]],"c":true},"ix":2},"nm":"Path 28","mn":"ADBE Vector Shape - Group","hd":false},{"ind":28,"ty":"sh","ix":29,"ks":{"a":0,"k":{"i":[[0,0]],"o":[[0,0]],"v":[[-108.191,72.123]],"c":false},"ix":2},"nm":"Path 29","mn":"ADBE Vector Shape - Group","hd":false},{"ind":29,"ty":"sh","ix":30,"ks":{"a":0,"k":{"i":[[0,0],[0,0],[0,0],[0,0]],"o":[[0,0],[0,0],[0,0],[0,0]],"v":[[-108.191,108.192],[-72.122,108.192],[-72.122,72.122],[-108.191,72.122]],"c":true},"ix":2},"nm":"Path 30","mn":"ADBE Vector Shape - Group","hd":false},{"ind":30,"ty":"sh","ix":31,"ks":{"a":0,"k":{"i":[[0,0]],"o":[[0,0]],"v":[[-108.191,72.123]],"c":false},"ix":2},"nm":"Path 31","mn":"ADBE Vector Shape - Group","hd":false},{"ind":31,"ty":"sh","ix":32,"ks":{"a":0,"k":{"i":[[0,0],[0,0],[0,0],[0,0]],"o":[[0,0],[0,0],[0,0],[0,0]],"v":[[-108.191,108.192],[-72.122,108.192],[-72.122,72.122],[-108.191,72.122]],"c":true},"ix":2},"nm":"Path 32","mn":"ADBE Vector Shape - Group","hd":false},{"ind":32,"ty":"sh","ix":33,"ks":{"a":0,"k":{"i":[[0,0]],"o":[[0,0]],"v":[[-108.191,72.123]],"c":false},"ix":2},"nm":"Path 33","mn":"ADBE Vector Shape - Group","hd":false},{"ind":33,"ty":"sh","ix":34,"ks":{"a":0,"k":{"i":[[0,0],[0,0],[0,0],[0,0]],"o":[[0,0],[0,0],[0,0],[0,0]],"v":[[-72.122,72.123],[-108.192,72.123],[-108.192,108.193],[-72.122,108.193]],"c":true},"ix":2},"nm":"Path 34","mn":"ADBE Vector Shape - Group","hd":false},{"ind":34,"ty":"sh","ix":35,"ks":{"a":0,"k":{"i":[[0,0],[0,0],[0,21.906],[0,0],[0,0]],"o":[[0,0],[-21.906,0],[0,0],[0,0],[0,0]],"v":[[-36.052,144.264],[-104.587,144.264],[-144.243,104.588],[-144.243,36.071],[-36.052,36.071]],"c":true},"ix":2},"nm":"Path 35","mn":"ADBE Vector Shape - Group","hd":false},{"ind":35,"ty":"sh","ix":36,"ks":{"a":0,"k":{"i":[[0,0],[0,0],[-31.861,0],[0,0],[0,0]],"o":[[0,0],[0,31.861],[0,0],[0,0],[0,0]],"v":[[-162.289,18.027],[-162.289,104.588],[-104.587,162.288],[-18.026,162.288],[-18.026,18.027]],"c":true},"ix":2},"nm":"Path 36","mn":"ADBE Vector Shape - Group","hd":false},{"ind":36,"ty":"sh","ix":37,"ks":{"a":0,"k":{"i":[[0,0],[0,0],[0,0],[0,0]],"o":[[0,0],[0,0],[0,0],[0,0]],"v":[[-108.191,108.192],[-72.122,108.192],[-72.122,72.122],[-108.191,72.122]],"c":true},"ix":2},"nm":"Path 37","mn":"ADBE Vector Shape - Group","hd":false},{"ind":37,"ty":"sh","ix":38,"ks":{"a":0,"k":{"i":[[0,0]],"o":[[0,0]],"v":[[-108.191,72.123]],"c":false},"ix":2},"nm":"Path 38","mn":"ADBE Vector Shape - Group","hd":false},{"ind":38,"ty":"sh","ix":39,"ks":{"a":0,"k":{"i":[[0,0],[0,0],[0,0],[0,0]],"o":[[0,0],[0,0],[0,0],[0,0]],"v":[[-108.191,108.192],[-72.122,108.192],[-72.122,72.122],[-108.191,72.122]],"c":true},"ix":2},"nm":"Path 39","mn":"ADBE Vector Shape - Group","hd":false},{"ind":39,"ty":"sh","ix":40,"ks":{"a":0,"k":{"i":[[0,0]],"o":[[0,0]],"v":[[-108.191,72.123]],"c":false},"ix":2},"nm":"Path 40","mn":"ADBE Vector Shape - Group","hd":false},{"ind":40,"ty":"sh","ix":41,"ks":{"a":0,"k":{"i":[[0,0],[0,0],[0,0],[0,0]],"o":[[0,0],[0,0],[0,0],[0,0]],"v":[[-108.191,108.192],[-72.122,108.192],[-72.122,72.122],[-108.191,72.122]],"c":true},"ix":2},"nm":"Path 41","mn":"ADBE Vector Shape - Group","hd":false},{"ind":41,"ty":"sh","ix":42,"ks":{"a":0,"k":{"i":[[0,0]],"o":[[0,0]],"v":[[-108.191,72.123]],"c":false},"ix":2},"nm":"Path 42","mn":"ADBE Vector Shape - Group","hd":false},{"ind":42,"ty":"sh","ix":43,"ks":{"a":0,"k":{"i":[[0,0],[0,0],[0,0],[0,0]],"o":[[0,0],[0,0],[0,0],[0,0]],"v":[[-108.191,108.192],[-72.122,108.192],[-72.122,72.122],[-108.191,72.122]],"c":true},"ix":2},"nm":"Path 43","mn":"ADBE Vector Shape - Group","hd":false},{"ind":43,"ty":"sh","ix":44,"ks":{"a":0,"k":{"i":[[0,0]],"o":[[0,0]],"v":[[-108.191,72.123]],"c":false},"ix":2},"nm":"Path 44","mn":"ADBE Vector Shape - Group","hd":false},{"ind":44,"ty":"sh","ix":45,"ks":{"a":0,"k":{"i":[[0,0],[0,0],[0,0],[0,0]],"o":[[0,0],[0,0],[0,0],[0,0]],"v":[[-108.191,-72.122],[-72.122,-72.122],[-72.122,-108.192],[-108.191,-108.192]],"c":true},"ix":2},"nm":"Path 45","mn":"ADBE Vector Shape - Group","hd":false},{"ind":45,"ty":"sh","ix":46,"ks":{"a":0,"k":{"i":[[0,0]],"o":[[0,0]],"v":[[-108.191,-108.191]],"c":false},"ix":2},"nm":"Path 46","mn":"ADBE Vector Shape - Group","hd":false},{"ind":46,"ty":"sh","ix":47,"ks":{"a":0,"k":{"i":[[0,0],[0,0],[0,0],[0,0]],"o":[[0,0],[0,0],[0,0],[0,0]],"v":[[-108.191,-72.122],[-72.122,-72.122],[-72.122,-108.192],[-108.191,-108.192]],"c":true},"ix":2},"nm":"Path 47","mn":"ADBE Vector Shape - Group","hd":false},{"ind":47,"ty":"sh","ix":48,"ks":{"a":0,"k":{"i":[[0,0]],"o":[[0,0]],"v":[[-108.191,-108.191]],"c":false},"ix":2},"nm":"Path 48","mn":"ADBE Vector Shape - Group","hd":false},{"ind":48,"ty":"sh","ix":49,"ks":{"a":0,"k":{"i":[[0,0],[0,0],[0,0],[0,0]],"o":[[0,0],[0,0],[0,0],[0,0]],"v":[[-108.191,-72.122],[-72.122,-72.122],[-72.122,-108.192],[-108.191,-108.192]],"c":true},"ix":2},"nm":"Path 49","mn":"ADBE Vector Shape - Group","hd":false},{"ind":49,"ty":"sh","ix":50,"ks":{"a":0,"k":{"i":[[0,0]],"o":[[0,0]],"v":[[-108.191,-108.191]],"c":false},"ix":2},"nm":"Path 50","mn":"ADBE Vector Shape - Group","hd":false},{"ind":50,"ty":"sh","ix":51,"ks":{"a":0,"k":{"i":[[0,0],[0,0],[0,0],[0,0]],"o":[[0,0],[0,0],[0,0],[0,0]],"v":[[-108.191,-72.122],[-72.122,-72.122],[-72.122,-108.192],[-108.191,-108.192]],"c":true},"ix":2},"nm":"Path 51","mn":"ADBE Vector Shape - Group","hd":false},{"ind":51,"ty":"sh","ix":52,"ks":{"a":0,"k":{"i":[[0,0],[0,0],[0,0],[-21.906,0],[0,0]],"o":[[0,0],[0,0],[0,-21.906],[0,0],[0,0]],"v":[[-36.052,-36.07],[-144.243,-36.07],[-144.243,-104.587],[-104.587,-144.262],[-36.052,-144.262]],"c":true},"ix":2},"nm":"Path 52","mn":"ADBE Vector Shape - Group","hd":false},{"ind":52,"ty":"sh","ix":53,"ks":{"a":0,"k":{"i":[[0,0],[0,-31.861],[0,0],[0,0],[0,0]],"o":[[-31.861,0],[0,0],[0,0],[0,0],[0,0]],"v":[[-104.587,-162.288],[-162.289,-104.587],[-162.289,-18.025],[-18.026,-18.025],[-18.026,-162.288]],"c":true},"ix":2},"nm":"Path 53","mn":"ADBE Vector Shape - Group","hd":false},{"ind":53,"ty":"sh","ix":54,"ks":{"a":0,"k":{"i":[[0,0],[0,0],[0,0],[0,0]],"o":[[0,0],[0,0],[0,0],[0,0]],"v":[[-108.191,-72.122],[-72.122,-72.122],[-72.122,-108.192],[-108.191,-108.192]],"c":true},"ix":2},"nm":"Path 54","mn":"ADBE Vector Shape - Group","hd":false},{"ind":54,"ty":"sh","ix":55,"ks":{"a":0,"k":{"i":[[0,0]],"o":[[0,0]],"v":[[-108.191,-108.191]],"c":false},"ix":2},"nm":"Path 55","mn":"ADBE Vector Shape - Group","hd":false},{"ind":55,"ty":"sh","ix":56,"ks":{"a":0,"k":{"i":[[0,0],[0,0],[0,0],[0,0]],"o":[[0,0],[0,0],[0,0],[0,0]],"v":[[-108.191,-72.122],[-72.122,-72.122],[-72.122,-108.192],[-108.191,-108.192]],"c":true},"ix":2},"nm":"Path 56","mn":"ADBE Vector Shape - Group","hd":false},{"ind":56,"ty":"sh","ix":57,"ks":{"a":0,"k":{"i":[[0,0]],"o":[[0,0]],"v":[[-108.191,-108.191]],"c":false},"ix":2},"nm":"Path 57","mn":"ADBE Vector Shape - Group","hd":false},{"ind":57,"ty":"sh","ix":58,"ks":{"a":0,"k":{"i":[[0,0],[0,0],[0,0],[0,0]],"o":[[0,0],[0,0],[0,0],[0,0]],"v":[[-108.191,-72.122],[-72.122,-72.122],[-72.122,-108.192],[-108.191,-108.192]],"c":true},"ix":2},"nm":"Path 58","mn":"ADBE Vector Shape - Group","hd":false},{"ind":58,"ty":"sh","ix":59,"ks":{"a":0,"k":{"i":[[0,0]],"o":[[0,0]],"v":[[-108.191,-108.191]],"c":false},"ix":2},"nm":"Path 59","mn":"ADBE Vector Shape - Group","hd":false},{"ind":59,"ty":"sh","ix":60,"ks":{"a":0,"k":{"i":[[0,0],[0,0],[0,0],[0,0]],"o":[[0,0],[0,0],[0,0],[0,0]],"v":[[-108.191,-72.122],[-72.122,-72.122],[-72.122,-108.192],[-108.191,-108.192]],"c":true},"ix":2},"nm":"Path 60","mn":"ADBE Vector Shape - Group","hd":false},{"ind":60,"ty":"sh","ix":61,"ks":{"a":0,"k":{"i":[[0,0]],"o":[[0,0]],"v":[[-108.191,-108.191]],"c":false},"ix":2},"nm":"Path 61","mn":"ADBE Vector Shape - Group","hd":false},{"ind":61,"ty":"sh","ix":62,"ks":{"a":0,"k":{"i":[[0,0],[0,0],[21.906,0],[0,0],[0,0],[0,0],[0,31.861],[0,0]],"o":[[0,0],[0,21.906],[0,0],[0,0],[0,0],[31.88,0],[0,0],[0,0]],"v":[[144.263,90.166],[144.263,104.588],[104.587,144.264],[72.141,144.264],[72.141,162.288],[104.587,162.288],[162.289,104.588],[162.289,90.166]],"c":true},"ix":2},"nm":"Path 62","mn":"ADBE Vector Shape - Group","hd":false},{"ind":62,"ty":"sh","ix":63,"ks":{"a":0,"k":{"i":[[0,0],[0,0],[0,0],[0,0],[0,0],[0,0]],"o":[[0,0],[0,0],[0,0],[0,0],[0,0],[0,0]],"v":[[126.237,18.027],[126.237,36.071],[144.263,36.071],[144.263,54.097],[162.289,54.097],[162.289,18.027]],"c":true},"ix":2},"nm":"Path 63","mn":"ADBE Vector Shape - Group","hd":false},{"ind":63,"ty":"sh","ix":64,"ks":{"a":0,"k":{"i":[[0,0],[0,0],[0,0],[0,0]],"o":[[0,0],[0,0],[0,0],[0,0]],"v":[[72.141,108.192],[108.193,108.192],[108.193,72.122],[72.141,72.122]],"c":true},"ix":2},"nm":"Path 64","mn":"ADBE Vector Shape - Group","hd":false},{"ind":64,"ty":"sh","ix":65,"ks":{"a":0,"k":{"i":[[0,0]],"o":[[0,0]],"v":[[72.141,72.123]],"c":false},"ix":2},"nm":"Path 65","mn":"ADBE Vector Shape - Group","hd":false},{"ind":65,"ty":"sh","ix":66,"ks":{"a":0,"k":{"i":[[0,0],[0,0],[0,0],[0,0],[0,0],[0,0]],"o":[[0,0],[0,0],[0,0],[0,0],[0,0],[0,0]],"v":[[18.044,18.027],[18.044,72.123],[36.07,72.123],[36.07,36.071],[108.193,36.071],[108.193,18.027]],"c":true},"ix":2},"nm":"Path 66","mn":"ADBE Vector Shape - Group","hd":false},{"ind":66,"ty":"sh","ix":67,"ks":{"a":0,"k":{"i":[[0,0],[0,0],[0,0],[0,0]],"o":[[0,0],[0,0],[0,0],[0,0]],"v":[[18.044,162.288],[36.07,162.288],[36.07,108.192],[18.044,108.192]],"c":true},"ix":2},"nm":"Path 67","mn":"ADBE Vector Shape - Group","hd":false},{"ty":"mm","mm":1,"nm":"Merge Paths 1","mn":"ADBE Vector Filter - Merge","hd":false},{"ty":"gr","it":[{"ind":0,"ty":"sh","ix":1,"ks":{"a":0,"k":{"i":[[0,0],[0,0],[0,0],[0,0]],"o":[[0,0],[0,0],[0,0],[0,0]],"v":[[-600,400],[600,400],[600,-400],[-600,-400]],"c":true},"ix":2},"nm":"Path 1","mn":"ADBE Vector Shape - Group","hd":false},{"ind":1,"ty":"sh","ix":2,"ks":{"a":0,"k":{"i":[[0,0],[0,0],[0,0],[0,0]],"o":[[0,0],[0,0],[0,0],[0,0]],"v":[[-600,-400],[600,-400],[600,400],[-600,400]],"c":true},"ix":2},"nm":"Path 2","mn":"ADBE Vector Shape - Group","hd":false},{"ty":"tr","p":{"a":0,"k":[0,0],"ix":2},"a":{"a":0,"k":[0,0],"ix":1},"s":{"a":0,"k":[100,100],"ix":3},"r":{"a":0,"k":0,"ix":6},"o":{"a":0,"k":100,"ix":7},"sk":{"a":0,"k":0,"ix":4},"sa":{"a":0,"k":0,"ix":5},"nm":"Transform"}],"nm":"Group 1","np":2,"cix":2,"ix":69,"mn":"ADBE Vector Group","hd":false},{"ty":"mm","mm":4,"nm":"Merge Paths 2","mn":"ADBE Vector Filter - Merge","hd":false},{"ty":"fl","c":{"a":0,"k":[0.435000011968,0.435000011968,0.435000011968,1],"ix":4},"o":{"a":0,"k":100,"ix":5},"r":1,"nm":"Fill 1","mn":"ADBE Vector Graphic - Fill","hd":false},{"ty":"tr","p":{"a":0,"k":[162.539,162.538],"ix":2},"a":{"a":0,"k":[0,0],"ix":1},"s":{"a":0,"k":[100,100],"ix":3},"r":{"a":0,"k":0,"ix":6},"o":{"a":0,"k":100,"ix":7},"sk":{"a":0,"k":0,"ix":4},"sa":{"a":0,"k":0,"ix":5},"nm":"Transform"}],"nm":"Group 1","np":71,"cix":2,"ix":1,"mn":"ADBE Vector Group","hd":false}],"ip":0,"op":240,"st":0,"bm":0},{"ddd":0,"ind":4,"ty":4,"nm":"magnifying-glass Outlines","sr":1,"ks":{"o":{"a":0,"k":100,"ix":11},"r":{"a":1,"k":[{"i":{"x":[0.8],"y":[1]},"o":{"x":[0.2],"y":[0]},"n":["0p8_1_0p2_0"],"t":0,"s":[-5],"e":[15]},{"i":{"x":[0.8],"y":[1]},"o":{"x":[0.2],"y":[0]},"n":["0p8_1_0p2_0"],"t":30,"s":[15],"e":[-12]},{"i":{"x":[0.8],"y":[1]},"o":{"x":[0.2],"y":[0]},"n":["0p8_1_0p2_0"],"t":60,"s":[-12],"e":[10]},{"i":{"x":[0.8],"y":[1]},"o":{"x":[0.2],"y":[0]},"n":["0p8_1_0p2_0"],"t":90,"s":[10],"e":[-5]},{"t":120}],"ix":10},"p":{"a":1,"k":[{"i":{"x":0.8,"y":1},"o":{"x":0.2,"y":0},"n":"0p8_1_0p2_0","t":0,"s":[844.678,643.457,0],"e":[912.284,711.062,0],"to":[0,0,0],"ti":[0,0,0]},{"i":{"x":0.8,"y":1},"o":{"x":0.2,"y":0},"n":"0p8_1_0p2_0","t":30,"s":[912.284,711.062,0],"e":[865.795,756.602,0],"to":[0,0,0],"ti":[0,0,0]},{"i":{"x":0.8,"y":1},"o":{"x":0.2,"y":0},"n":"0p8_1_0p2_0","t":60,"s":[865.795,756.602,0],"e":[922.842,877.495,0],"to":[0,0,0],"ti":[0,0,0]},{"i":{"x":0.8,"y":1},"o":{"x":0.2,"y":0},"n":"0p8_1_0p2_0","t":90,"s":[922.842,877.495,0],"e":[844.678,643.457,0],"to":[0,0,0],"ti":[0,0,0]},{"t":120}],"ix":2},"a":{"a":0,"k":[319.819,319.821,0],"ix":1},"s":{"a":0,"k":[150,150,100],"ix":6}},"ao":0,"shapes":[{"ty":"gr","it":[{"ind":0,"ty":"sh","ix":1,"ks":{"a":0,"k":{"i":[[46.457,0.001],[0.001,46.634],[-46.456,-0.003],[-0.002,-46.631]],"o":[[-46.634,-0.001],[-0.001,-46.457],[46.633,0.003],[0.003,46.457]],"v":[[-38.849,45.436],[-123.129,-38.844],[-38.842,-123.128],[45.435,-38.851]],"c":true},"ix":2},"nm":"Path 1","mn":"ADBE Vector Shape - Group","hd":false},{"ind":1,"ty":"sh","ix":2,"ks":{"a":0,"k":{"i":[[3.011,0],[0,0],[0,0],[1.216,31.971],[64.985,0.158],[-0.162,-67.476],[-64.939,-2.47],[-22.458,19.305],[0,0],[0,0],[-2.131,-2.127],[0,0],[-7.708,7.709],[7.7,7.717],[0,0]],"o":[[0,0],[0,0],[19.307,-22.458],[-2.469,-64.939],[-67.477,-0.164],[0.156,64.986],[31.973,1.216],[0,0],[0,0],[0,3.01],[0,0],[7.716,7.701],[7.709,-7.708],[0,0],[-2.127,-2.132]],"v":[[68.825,45.436],[58.734,45.436],[53.488,40.379],[82.804,-43.554],[-38.544,-160.586],[-160.587,-38.547],[-43.557,82.805],[40.378,53.49],[45.435,58.734],[45.435,68.828],[48.764,76.852],[125.114,153.049],[153.034,153.036],[153.049,125.115],[76.851,48.765]],"c":true},"ix":2},"nm":"Path 2","mn":"ADBE Vector Shape - Group","hd":false},{"ty":"mm","mm":1,"nm":"Merge Paths 1","mn":"ADBE Vector Filter - Merge","hd":false},{"ty":"mm","mm":4,"nm":"Merge Paths 2","mn":"ADBE Vector Filter - Merge","hd":false},{"ty":"fl","c":{"a":0,"k":[0.639215686275,0.803921568627,1,1],"ix":4},"o":{"a":0,"k":100,"ix":5},"r":1,"nm":"Fill 1","mn":"ADBE Vector Graphic - Fill","hd":false},{"ty":"tr","p":{"a":0,"k":[160.999,161],"ix":2},"a":{"a":0,"k":[0,0],"ix":1},"s":{"a":0,"k":[100,100],"ix":3},"r":{"a":0,"k":0,"ix":6},"o":{"a":0,"k":100,"ix":7},"sk":{"a":0,"k":0,"ix":4},"sa":{"a":0,"k":0,"ix":5},"nm":"Transform"}],"nm":"Group 2","np":5,"cix":2,"ix":1,"mn":"ADBE Vector Group","hd":false}],"ip":0,"op":240,"st":0,"bm":0},{"ddd":0,"ind":5,"ty":4,"nm":"mask 2","td":1,"sr":1,"ks":{"o":{"a":0,"k":100,"ix":11},"r":{"a":1,"k":[{"i":{"x":[0.8],"y":[1]},"o":{"x":[0.2],"y":[0]},"n":["0p8_1_0p2_0"],"t":0,"s":[-5],"e":[15]},{"i":{"x":[0.8],"y":[1]},"o":{"x":[0.2],"y":[0]},"n":["0p8_1_0p2_0"],"t":30,"s":[15],"e":[-12]},{"i":{"x":[0.8],"y":[1]},"o":{"x":[0.2],"y":[0]},"n":["0p8_1_0p2_0"],"t":60,"s":[-12],"e":[10]},{"i":{"x":[0.8],"y":[1]},"o":{"x":[0.2],"y":[0]},"n":["0p8_1_0p2_0"],"t":90,"s":[10],"e":[-5]},{"t":120}],"ix":10},"p":{"a":1,"k":[{"i":{"x":0.8,"y":1},"o":{"x":0.2,"y":0},"n":"0p8_1_0p2_0","t":0,"s":[844.678,643.457,0],"e":[912.284,711.062,0],"to":[0,0,0],"ti":[0,0,0]},{"i":{"x":0.8,"y":1},"o":{"x":0.2,"y":0},"n":"0p8_1_0p2_0","t":30,"s":[912.284,711.062,0],"e":[865.795,756.602,0],"to":[0,0,0],"ti":[0,0,0]},{"i":{"x":0.8,"y":1},"o":{"x":0.2,"y":0},"n":"0p8_1_0p2_0","t":60,"s":[865.795,756.602,0],"e":[922.842,877.495,0],"to":[0,0,0],"ti":[0,0,0]},{"i":{"x":0.8,"y":1},"o":{"x":0.2,"y":0},"n":"0p8_1_0p2_0","t":90,"s":[922.842,877.495,0],"e":[844.678,643.457,0],"to":[0,0,0],"ti":[0,0,0]},{"t":120}],"ix":2},"a":{"a":0,"k":[319.819,319.821,0],"ix":1},"s":{"a":0,"k":[150,150,100],"ix":6}},"ao":0,"shapes":[{"ty":"gr","it":[{"ind":0,"ty":"sh","ix":1,"ks":{"a":0,"k":{"i":[[46.637,0],[0,46.636],[-46.635,0],[0,-46.636]],"o":[[-46.635,0],[0,-46.636],[46.637,0],[0,46.636]],"v":[[-0.001,84.282],[-84.282,0],[-0.001,-84.282],[84.282,0]],"c":true},"ix":2},"nm":"Path 1","mn":"ADBE Vector Shape - Group","hd":false},{"ty":"fl","c":{"a":0,"k":[0,0,0,1],"ix":4},"o":{"a":0,"k":100,"ix":5},"r":1,"nm":"Fill 1","mn":"ADBE Vector Graphic - Fill","hd":false},{"ty":"tr","p":{"a":0,"k":[122.152,122.154],"ix":2},"a":{"a":0,"k":[0,0],"ix":1},"s":{"a":0,"k":[100,100],"ix":3},"r":{"a":0,"k":0,"ix":6},"o":{"a":0,"k":100,"ix":7},"sk":{"a":0,"k":0,"ix":4},"sa":{"a":0,"k":0,"ix":5},"nm":"Transform"}],"nm":"Group 1","np":2,"cix":2,"ix":1,"mn":"ADBE Vector Group","hd":false}],"ip":0,"op":240,"st":0,"bm":0},{"ddd":0,"ind":6,"ty":4,"nm":"qr Outlines","tt":2,"sr":1,"ks":{"o":{"a":0,"k":100,"ix":11},"r":{"a":0,"k":0,"ix":10},"p":{"a":0,"k":[600,449.999,0],"ix":2},"a":{"a":0,"k":[162.539,162.538,0],"ix":1},"s":{"a":0,"k":[100,100,100],"ix":6}},"ao":0,"shapes":[{"ty":"gr","it":[{"ind":0,"ty":"sh","ix":1,"ks":{"a":0,"k":{"i":[[0,0],[0,0],[0,0],[0,0]],"o":[[0,0],[0,0],[0,0],[0,0]],"v":[[72.141,-72.122],[108.193,-72.122],[108.193,-108.192],[72.141,-108.192]],"c":true},"ix":2},"nm":"Path 1","mn":"ADBE Vector Shape - Group","hd":false},{"ind":1,"ty":"sh","ix":2,"ks":{"a":0,"k":{"i":[[0,0]],"o":[[0,0]],"v":[[72.141,-108.191]],"c":false},"ix":2},"nm":"Path 2","mn":"ADBE Vector Shape - Group","hd":false},{"ind":2,"ty":"sh","ix":3,"ks":{"a":0,"k":{"i":[[0,0],[0,0],[0,0],[0,0]],"o":[[0,0],[0,0],[0,0],[0,0]],"v":[[72.141,108.192],[108.193,108.192],[108.193,72.122],[72.141,72.122]],"c":true},"ix":2},"nm":"Path 3","mn":"ADBE Vector Shape - Group","hd":false},{"ind":3,"ty":"sh","ix":4,"ks":{"a":0,"k":{"i":[[0,0]],"o":[[0,0]],"v":[[72.141,72.123]],"c":false},"ix":2},"nm":"Path 4","mn":"ADBE Vector Shape - Group","hd":false},{"ind":4,"ty":"sh","ix":5,"ks":{"a":0,"k":{"i":[[0,0],[0,0],[0,0],[0,0]],"o":[[0,0],[0,0],[0,0],[0,0]],"v":[[-108.191,108.192],[-72.122,108.192],[-72.122,72.122],[-108.191,72.122]],"c":true},"ix":2},"nm":"Path 5","mn":"ADBE Vector Shape - Group","hd":false},{"ind":5,"ty":"sh","ix":6,"ks":{"a":0,"k":{"i":[[0,0]],"o":[[0,0]],"v":[[-108.191,72.123]],"c":false},"ix":2},"nm":"Path 6","mn":"ADBE Vector Shape - Group","hd":false},{"ind":6,"ty":"sh","ix":7,"ks":{"a":0,"k":{"i":[[0,0],[0,0],[0,0],[0,0]],"o":[[0,0],[0,0],[0,0],[0,0]],"v":[[-108.191,-72.122],[-72.122,-72.122],[-72.122,-108.192],[-108.191,-108.192]],"c":true},"ix":2},"nm":"Path 7","mn":"ADBE Vector Shape - Group","hd":false},{"ind":7,"ty":"sh","ix":8,"ks":{"a":0,"k":{"i":[[0,0]],"o":[[0,0]],"v":[[-108.191,-108.191]],"c":false},"ix":2},"nm":"Path 8","mn":"ADBE Vector Shape - Group","hd":false},{"ind":8,"ty":"sh","ix":9,"ks":{"a":0,"k":{"i":[[0,0],[0,0],[0,0],[0,0]],"o":[[0,0],[0,0],[0,0],[0,0]],"v":[[72.141,-72.122],[108.193,-72.122],[108.193,-108.192],[72.141,-108.192]],"c":true},"ix":2},"nm":"Path 9","mn":"ADBE Vector Shape - Group","hd":false},{"ind":9,"ty":"sh","ix":10,"ks":{"a":0,"k":{"i":[[0,0]],"o":[[0,0]],"v":[[72.141,-108.191]],"c":false},"ix":2},"nm":"Path 10","mn":"ADBE Vector Shape - Group","hd":false},{"ind":10,"ty":"sh","ix":11,"ks":{"a":0,"k":{"i":[[0,0],[0,0],[0,0],[0,0]],"o":[[0,0],[0,0],[0,0],[0,0]],"v":[[72.141,-72.122],[108.193,-72.122],[108.193,-108.192],[72.141,-108.192]],"c":true},"ix":2},"nm":"Path 11","mn":"ADBE Vector Shape - Group","hd":false},{"ind":11,"ty":"sh","ix":12,"ks":{"a":0,"k":{"i":[[0,0]],"o":[[0,0]],"v":[[72.141,-108.191]],"c":false},"ix":2},"nm":"Path 12","mn":"ADBE Vector Shape - Group","hd":false},{"ind":12,"ty":"sh","ix":13,"ks":{"a":0,"k":{"i":[[0,0],[0,0],[0,0],[0,0]],"o":[[0,0],[0,0],[0,0],[0,0]],"v":[[72.141,-72.122],[108.193,-72.122],[108.193,-108.192],[72.141,-108.192]],"c":true},"ix":2},"nm":"Path 13","mn":"ADBE Vector Shape - Group","hd":false},{"ind":13,"ty":"sh","ix":14,"ks":{"a":0,"k":{"i":[[0,0]],"o":[[0,0]],"v":[[72.141,-108.191]],"c":false},"ix":2},"nm":"Path 14","mn":"ADBE Vector Shape - Group","hd":false},{"ind":14,"ty":"sh","ix":15,"ks":{"a":0,"k":{"i":[[0,0],[0,0],[0,0],[0,0]],"o":[[0,0],[0,0],[0,0],[0,0]],"v":[[72.141,-72.122],[108.193,-72.122],[108.193,-108.192],[72.141,-108.192]],"c":true},"ix":2},"nm":"Path 15","mn":"ADBE Vector Shape - Group","hd":false},{"ind":15,"ty":"sh","ix":16,"ks":{"a":0,"k":{"i":[[0,0],[0,0],[0,0],[0,0],[0,-21.906]],"o":[[0,0],[0,0],[0,0],[21.906,0],[0,0]],"v":[[144.263,-36.07],[36.07,-36.07],[36.07,-144.262],[104.587,-144.262],[144.263,-104.587]],"c":true},"ix":2},"nm":"Path 16","mn":"ADBE Vector Shape - Group","hd":false},{"ind":16,"ty":"sh","ix":17,"ks":{"a":0,"k":{"i":[[31.88,0],[0,0],[0,0],[0,0],[0,0]],"o":[[0,0],[0,0],[0,0],[0,0],[0,-31.861]],"v":[[104.587,-162.288],[18.044,-162.288],[18.044,-18.025],[162.289,-18.025],[162.289,-104.587]],"c":true},"ix":2},"nm":"Path 17","mn":"ADBE Vector Shape - Group","hd":false},{"ind":17,"ty":"sh","ix":18,"ks":{"a":0,"k":{"i":[[0,0],[0,0],[0,0],[0,0]],"o":[[0,0],[0,0],[0,0],[0,0]],"v":[[72.141,-72.122],[108.193,-72.122],[108.193,-108.192],[72.141,-108.192]],"c":true},"ix":2},"nm":"Path 18","mn":"ADBE Vector Shape - Group","hd":false},{"ind":18,"ty":"sh","ix":19,"ks":{"a":0,"k":{"i":[[0,0]],"o":[[0,0]],"v":[[72.141,-108.191]],"c":false},"ix":2},"nm":"Path 19","mn":"ADBE Vector Shape - Group","hd":false},{"ind":19,"ty":"sh","ix":20,"ks":{"a":0,"k":{"i":[[0,0],[0,0],[0,0],[0,0]],"o":[[0,0],[0,0],[0,0],[0,0]],"v":[[72.141,-72.122],[108.193,-72.122],[108.193,-108.192],[72.141,-108.192]],"c":true},"ix":2},"nm":"Path 20","mn":"ADBE Vector Shape - Group","hd":false},{"ind":20,"ty":"sh","ix":21,"ks":{"a":0,"k":{"i":[[0,0]],"o":[[0,0]],"v":[[72.141,-108.191]],"c":false},"ix":2},"nm":"Path 21","mn":"ADBE Vector Shape - Group","hd":false},{"ind":21,"ty":"sh","ix":22,"ks":{"a":0,"k":{"i":[[0,0],[0,0],[0,0],[0,0]],"o":[[0,0],[0,0],[0,0],[0,0]],"v":[[72.141,-72.122],[108.193,-72.122],[108.193,-108.192],[72.141,-108.192]],"c":true},"ix":2},"nm":"Path 22","mn":"ADBE Vector Shape - Group","hd":false},{"ind":22,"ty":"sh","ix":23,"ks":{"a":0,"k":{"i":[[0,0]],"o":[[0,0]],"v":[[72.141,-108.191]],"c":false},"ix":2},"nm":"Path 23","mn":"ADBE Vector Shape - Group","hd":false},{"ind":23,"ty":"sh","ix":24,"ks":{"a":0,"k":{"i":[[0,0],[0,0],[0,0],[0,0]],"o":[[0,0],[0,0],[0,0],[0,0]],"v":[[72.141,-72.122],[108.193,-72.122],[108.193,-108.192],[72.141,-108.192]],"c":true},"ix":2},"nm":"Path 24","mn":"ADBE Vector Shape - Group","hd":false},{"ind":24,"ty":"sh","ix":25,"ks":{"a":0,"k":{"i":[[0,0]],"o":[[0,0]],"v":[[72.141,-108.191]],"c":false},"ix":2},"nm":"Path 25","mn":"ADBE Vector Shape - Group","hd":false},{"ind":25,"ty":"sh","ix":26,"ks":{"a":0,"k":{"i":[[0,0],[0,0],[0,0],[0,0]],"o":[[0,0],[0,0],[0,0],[0,0]],"v":[[72.141,108.192],[108.193,108.192],[108.193,72.122],[72.141,72.122]],"c":true},"ix":2},"nm":"Path 26","mn":"ADBE Vector Shape - Group","hd":false},{"ind":26,"ty":"sh","ix":27,"ks":{"a":0,"k":{"i":[[0,0]],"o":[[0,0]],"v":[[72.141,72.123]],"c":false},"ix":2},"nm":"Path 27","mn":"ADBE Vector Shape - Group","hd":false},{"ind":27,"ty":"sh","ix":28,"ks":{"a":0,"k":{"i":[[0,0],[0,0],[0,0],[0,0]],"o":[[0,0],[0,0],[0,0],[0,0]],"v":[[-108.191,108.192],[-72.122,108.192],[-72.122,72.122],[-108.191,72.122]],"c":true},"ix":2},"nm":"Path 28","mn":"ADBE Vector Shape - Group","hd":false},{"ind":28,"ty":"sh","ix":29,"ks":{"a":0,"k":{"i":[[0,0]],"o":[[0,0]],"v":[[-108.191,72.123]],"c":false},"ix":2},"nm":"Path 29","mn":"ADBE Vector Shape - Group","hd":false},{"ind":29,"ty":"sh","ix":30,"ks":{"a":0,"k":{"i":[[0,0],[0,0],[0,0],[0,0]],"o":[[0,0],[0,0],[0,0],[0,0]],"v":[[-108.191,108.192],[-72.122,108.192],[-72.122,72.122],[-108.191,72.122]],"c":true},"ix":2},"nm":"Path 30","mn":"ADBE Vector Shape - Group","hd":false},{"ind":30,"ty":"sh","ix":31,"ks":{"a":0,"k":{"i":[[0,0]],"o":[[0,0]],"v":[[-108.191,72.123]],"c":false},"ix":2},"nm":"Path 31","mn":"ADBE Vector Shape - Group","hd":false},{"ind":31,"ty":"sh","ix":32,"ks":{"a":0,"k":{"i":[[0,0],[0,0],[0,0],[0,0]],"o":[[0,0],[0,0],[0,0],[0,0]],"v":[[-108.191,108.192],[-72.122,108.192],[-72.122,72.122],[-108.191,72.122]],"c":true},"ix":2},"nm":"Path 32","mn":"ADBE Vector Shape - Group","hd":false},{"ind":32,"ty":"sh","ix":33,"ks":{"a":0,"k":{"i":[[0,0]],"o":[[0,0]],"v":[[-108.191,72.123]],"c":false},"ix":2},"nm":"Path 33","mn":"ADBE Vector Shape - Group","hd":false},{"ind":33,"ty":"sh","ix":34,"ks":{"a":0,"k":{"i":[[0,0],[0,0],[0,0],[0,0]],"o":[[0,0],[0,0],[0,0],[0,0]],"v":[[-72.122,72.123],[-108.192,72.123],[-108.192,108.193],[-72.122,108.193]],"c":true},"ix":2},"nm":"Path 34","mn":"ADBE Vector Shape - Group","hd":false},{"ind":34,"ty":"sh","ix":35,"ks":{"a":0,"k":{"i":[[0,0],[0,0],[0,21.906],[0,0],[0,0]],"o":[[0,0],[-21.906,0],[0,0],[0,0],[0,0]],"v":[[-36.052,144.264],[-104.587,144.264],[-144.243,104.588],[-144.243,36.071],[-36.052,36.071]],"c":true},"ix":2},"nm":"Path 35","mn":"ADBE Vector Shape - Group","hd":false},{"ind":35,"ty":"sh","ix":36,"ks":{"a":0,"k":{"i":[[0,0],[0,0],[-31.861,0],[0,0],[0,0]],"o":[[0,0],[0,31.861],[0,0],[0,0],[0,0]],"v":[[-162.289,18.027],[-162.289,104.588],[-104.587,162.288],[-18.026,162.288],[-18.026,18.027]],"c":true},"ix":2},"nm":"Path 36","mn":"ADBE Vector Shape - Group","hd":false},{"ind":36,"ty":"sh","ix":37,"ks":{"a":0,"k":{"i":[[0,0],[0,0],[0,0],[0,0]],"o":[[0,0],[0,0],[0,0],[0,0]],"v":[[-108.191,108.192],[-72.122,108.192],[-72.122,72.122],[-108.191,72.122]],"c":true},"ix":2},"nm":"Path 37","mn":"ADBE Vector Shape - Group","hd":false},{"ind":37,"ty":"sh","ix":38,"ks":{"a":0,"k":{"i":[[0,0]],"o":[[0,0]],"v":[[-108.191,72.123]],"c":false},"ix":2},"nm":"Path 38","mn":"ADBE Vector Shape - Group","hd":false},{"ind":38,"ty":"sh","ix":39,"ks":{"a":0,"k":{"i":[[0,0],[0,0],[0,0],[0,0]],"o":[[0,0],[0,0],[0,0],[0,0]],"v":[[-108.191,108.192],[-72.122,108.192],[-72.122,72.122],[-108.191,72.122]],"c":true},"ix":2},"nm":"Path 39","mn":"ADBE Vector Shape - Group","hd":false},{"ind":39,"ty":"sh","ix":40,"ks":{"a":0,"k":{"i":[[0,0]],"o":[[0,0]],"v":[[-108.191,72.123]],"c":false},"ix":2},"nm":"Path 40","mn":"ADBE Vector Shape - Group","hd":false},{"ind":40,"ty":"sh","ix":41,"ks":{"a":0,"k":{"i":[[0,0],[0,0],[0,0],[0,0]],"o":[[0,0],[0,0],[0,0],[0,0]],"v":[[-108.191,108.192],[-72.122,108.192],[-72.122,72.122],[-108.191,72.122]],"c":true},"ix":2},"nm":"Path 41","mn":"ADBE Vector Shape - Group","hd":false},{"ind":41,"ty":"sh","ix":42,"ks":{"a":0,"k":{"i":[[0,0]],"o":[[0,0]],"v":[[-108.191,72.123]],"c":false},"ix":2},"nm":"Path 42","mn":"ADBE Vector Shape - Group","hd":false},{"ind":42,"ty":"sh","ix":43,"ks":{"a":0,"k":{"i":[[0,0],[0,0],[0,0],[0,0]],"o":[[0,0],[0,0],[0,0],[0,0]],"v":[[-108.191,108.192],[-72.122,108.192],[-72.122,72.122],[-108.191,72.122]],"c":true},"ix":2},"nm":"Path 43","mn":"ADBE Vector Shape - Group","hd":false},{"ind":43,"ty":"sh","ix":44,"ks":{"a":0,"k":{"i":[[0,0]],"o":[[0,0]],"v":[[-108.191,72.123]],"c":false},"ix":2},"nm":"Path 44","mn":"ADBE Vector Shape - Group","hd":false},{"ind":44,"ty":"sh","ix":45,"ks":{"a":0,"k":{"i":[[0,0],[0,0],[0,0],[0,0]],"o":[[0,0],[0,0],[0,0],[0,0]],"v":[[-108.191,-72.122],[-72.122,-72.122],[-72.122,-108.192],[-108.191,-108.192]],"c":true},"ix":2},"nm":"Path 45","mn":"ADBE Vector Shape - Group","hd":false},{"ind":45,"ty":"sh","ix":46,"ks":{"a":0,"k":{"i":[[0,0]],"o":[[0,0]],"v":[[-108.191,-108.191]],"c":false},"ix":2},"nm":"Path 46","mn":"ADBE Vector Shape - Group","hd":false},{"ind":46,"ty":"sh","ix":47,"ks":{"a":0,"k":{"i":[[0,0],[0,0],[0,0],[0,0]],"o":[[0,0],[0,0],[0,0],[0,0]],"v":[[-108.191,-72.122],[-72.122,-72.122],[-72.122,-108.192],[-108.191,-108.192]],"c":true},"ix":2},"nm":"Path 47","mn":"ADBE Vector Shape - Group","hd":false},{"ind":47,"ty":"sh","ix":48,"ks":{"a":0,"k":{"i":[[0,0]],"o":[[0,0]],"v":[[-108.191,-108.191]],"c":false},"ix":2},"nm":"Path 48","mn":"ADBE Vector Shape - Group","hd":false},{"ind":48,"ty":"sh","ix":49,"ks":{"a":0,"k":{"i":[[0,0],[0,0],[0,0],[0,0]],"o":[[0,0],[0,0],[0,0],[0,0]],"v":[[-108.191,-72.122],[-72.122,-72.122],[-72.122,-108.192],[-108.191,-108.192]],"c":true},"ix":2},"nm":"Path 49","mn":"ADBE Vector Shape - Group","hd":false},{"ind":49,"ty":"sh","ix":50,"ks":{"a":0,"k":{"i":[[0,0]],"o":[[0,0]],"v":[[-108.191,-108.191]],"c":false},"ix":2},"nm":"Path 50","mn":"ADBE Vector Shape - Group","hd":false},{"ind":50,"ty":"sh","ix":51,"ks":{"a":0,"k":{"i":[[0,0],[0,0],[0,0],[0,0]],"o":[[0,0],[0,0],[0,0],[0,0]],"v":[[-108.191,-72.122],[-72.122,-72.122],[-72.122,-108.192],[-108.191,-108.192]],"c":true},"ix":2},"nm":"Path 51","mn":"ADBE Vector Shape - Group","hd":false},{"ind":51,"ty":"sh","ix":52,"ks":{"a":0,"k":{"i":[[0,0],[0,0],[0,0],[-21.906,0],[0,0]],"o":[[0,0],[0,0],[0,-21.906],[0,0],[0,0]],"v":[[-36.052,-36.07],[-144.243,-36.07],[-144.243,-104.587],[-104.587,-144.262],[-36.052,-144.262]],"c":true},"ix":2},"nm":"Path 52","mn":"ADBE Vector Shape - Group","hd":false},{"ind":52,"ty":"sh","ix":53,"ks":{"a":0,"k":{"i":[[0,0],[0,-31.861],[0,0],[0,0],[0,0]],"o":[[-31.861,0],[0,0],[0,0],[0,0],[0,0]],"v":[[-104.587,-162.288],[-162.289,-104.587],[-162.289,-18.025],[-18.026,-18.025],[-18.026,-162.288]],"c":true},"ix":2},"nm":"Path 53","mn":"ADBE Vector Shape - Group","hd":false},{"ind":53,"ty":"sh","ix":54,"ks":{"a":0,"k":{"i":[[0,0],[0,0],[0,0],[0,0]],"o":[[0,0],[0,0],[0,0],[0,0]],"v":[[-108.191,-72.122],[-72.122,-72.122],[-72.122,-108.192],[-108.191,-108.192]],"c":true},"ix":2},"nm":"Path 54","mn":"ADBE Vector Shape - Group","hd":false},{"ind":54,"ty":"sh","ix":55,"ks":{"a":0,"k":{"i":[[0,0]],"o":[[0,0]],"v":[[-108.191,-108.191]],"c":false},"ix":2},"nm":"Path 55","mn":"ADBE Vector Shape - Group","hd":false},{"ind":55,"ty":"sh","ix":56,"ks":{"a":0,"k":{"i":[[0,0],[0,0],[0,0],[0,0]],"o":[[0,0],[0,0],[0,0],[0,0]],"v":[[-108.191,-72.122],[-72.122,-72.122],[-72.122,-108.192],[-108.191,-108.192]],"c":true},"ix":2},"nm":"Path 56","mn":"ADBE Vector Shape - Group","hd":false},{"ind":56,"ty":"sh","ix":57,"ks":{"a":0,"k":{"i":[[0,0]],"o":[[0,0]],"v":[[-108.191,-108.191]],"c":false},"ix":2},"nm":"Path 57","mn":"ADBE Vector Shape - Group","hd":false},{"ind":57,"ty":"sh","ix":58,"ks":{"a":0,"k":{"i":[[0,0],[0,0],[0,0],[0,0]],"o":[[0,0],[0,0],[0,0],[0,0]],"v":[[-108.191,-72.122],[-72.122,-72.122],[-72.122,-108.192],[-108.191,-108.192]],"c":true},"ix":2},"nm":"Path 58","mn":"ADBE Vector Shape - Group","hd":false},{"ind":58,"ty":"sh","ix":59,"ks":{"a":0,"k":{"i":[[0,0]],"o":[[0,0]],"v":[[-108.191,-108.191]],"c":false},"ix":2},"nm":"Path 59","mn":"ADBE Vector Shape - Group","hd":false},{"ind":59,"ty":"sh","ix":60,"ks":{"a":0,"k":{"i":[[0,0],[0,0],[0,0],[0,0]],"o":[[0,0],[0,0],[0,0],[0,0]],"v":[[-108.191,-72.122],[-72.122,-72.122],[-72.122,-108.192],[-108.191,-108.192]],"c":true},"ix":2},"nm":"Path 60","mn":"ADBE Vector Shape - Group","hd":false},{"ind":60,"ty":"sh","ix":61,"ks":{"a":0,"k":{"i":[[0,0]],"o":[[0,0]],"v":[[-108.191,-108.191]],"c":false},"ix":2},"nm":"Path 61","mn":"ADBE Vector Shape - Group","hd":false},{"ind":61,"ty":"sh","ix":62,"ks":{"a":0,"k":{"i":[[0,0],[0,0],[21.906,0],[0,0],[0,0],[0,0],[0,31.861],[0,0]],"o":[[0,0],[0,21.906],[0,0],[0,0],[0,0],[31.88,0],[0,0],[0,0]],"v":[[144.263,90.166],[144.263,104.588],[104.587,144.264],[72.141,144.264],[72.141,162.288],[104.587,162.288],[162.289,104.588],[162.289,90.166]],"c":true},"ix":2},"nm":"Path 62","mn":"ADBE Vector Shape - Group","hd":false},{"ind":62,"ty":"sh","ix":63,"ks":{"a":0,"k":{"i":[[0,0],[0,0],[0,0],[0,0],[0,0],[0,0]],"o":[[0,0],[0,0],[0,0],[0,0],[0,0],[0,0]],"v":[[126.237,18.027],[126.237,36.071],[144.263,36.071],[144.263,54.097],[162.289,54.097],[162.289,18.027]],"c":true},"ix":2},"nm":"Path 63","mn":"ADBE Vector Shape - Group","hd":false},{"ind":63,"ty":"sh","ix":64,"ks":{"a":0,"k":{"i":[[0,0],[0,0],[0,0],[0,0]],"o":[[0,0],[0,0],[0,0],[0,0]],"v":[[72.141,108.192],[108.193,108.192],[108.193,72.122],[72.141,72.122]],"c":true},"ix":2},"nm":"Path 64","mn":"ADBE Vector Shape - Group","hd":false},{"ind":64,"ty":"sh","ix":65,"ks":{"a":0,"k":{"i":[[0,0]],"o":[[0,0]],"v":[[72.141,72.123]],"c":false},"ix":2},"nm":"Path 65","mn":"ADBE Vector Shape - Group","hd":false},{"ind":65,"ty":"sh","ix":66,"ks":{"a":0,"k":{"i":[[0,0],[0,0],[0,0],[0,0],[0,0],[0,0]],"o":[[0,0],[0,0],[0,0],[0,0],[0,0],[0,0]],"v":[[18.044,18.027],[18.044,72.123],[36.07,72.123],[36.07,36.071],[108.193,36.071],[108.193,18.027]],"c":true},"ix":2},"nm":"Path 66","mn":"ADBE Vector Shape - Group","hd":false},{"ind":66,"ty":"sh","ix":67,"ks":{"a":0,"k":{"i":[[0,0],[0,0],[0,0],[0,0]],"o":[[0,0],[0,0],[0,0],[0,0]],"v":[[18.044,162.288],[36.07,162.288],[36.07,108.192],[18.044,108.192]],"c":true},"ix":2},"nm":"Path 67","mn":"ADBE Vector Shape - Group","hd":false},{"ty":"mm","mm":1,"nm":"Merge Paths 1","mn":"ADBE Vector Filter - Merge","hd":false},{"ty":"gr","it":[{"ind":0,"ty":"sh","ix":1,"ks":{"a":0,"k":{"i":[[0,0],[0,0],[0,0],[0,0]],"o":[[0,0],[0,0],[0,0],[0,0]],"v":[[-600,400],[600,400],[600,-400],[-600,-400]],"c":true},"ix":2},"nm":"Path 1","mn":"ADBE Vector Shape - Group","hd":false},{"ind":1,"ty":"sh","ix":2,"ks":{"a":0,"k":{"i":[[0,0],[0,0],[0,0],[0,0]],"o":[[0,0],[0,0],[0,0],[0,0]],"v":[[-600,-400],[600,-400],[600,400],[-600,400]],"c":true},"ix":2},"nm":"Path 2","mn":"ADBE Vector Shape - Group","hd":false},{"ty":"tr","p":{"a":0,"k":[0,0],"ix":2},"a":{"a":0,"k":[0,0],"ix":1},"s":{"a":0,"k":[100,100],"ix":3},"r":{"a":0,"k":0,"ix":6},"o":{"a":0,"k":100,"ix":7},"sk":{"a":0,"k":0,"ix":4},"sa":{"a":0,"k":0,"ix":5},"nm":"Transform"}],"nm":"Group 1","np":2,"cix":2,"ix":69,"mn":"ADBE Vector Group","hd":false},{"ty":"mm","mm":4,"nm":"Merge Paths 2","mn":"ADBE Vector Filter - Merge","hd":false},{"ty":"fl","c":{"a":0,"k":[0.435000011968,0.435000011968,0.435000011968,1],"ix":4},"o":{"a":0,"k":100,"ix":5},"r":1,"nm":"Fill 1","mn":"ADBE Vector Graphic - Fill","hd":false},{"ty":"tr","p":{"a":0,"k":[162.539,162.538],"ix":2},"a":{"a":0,"k":[0,0],"ix":1},"s":{"a":0,"k":[100,100],"ix":3},"r":{"a":0,"k":0,"ix":6},"o":{"a":0,"k":100,"ix":7},"sk":{"a":0,"k":0,"ix":4},"sa":{"a":0,"k":0,"ix":5},"nm":"Transform"}],"nm":"Group 1","np":71,"cix":2,"ix":1,"mn":"ADBE Vector Group","hd":false}],"ip":0,"op":240,"st":0,"bm":0}]}],"layers":[{"ddd":0,"ind":1,"ty":0,"nm":"seedsearch-animation-pre","refId":"comp_0","sr":1,"ks":{"o":{"a":0,"k":100,"ix":11},"r":{"a":0,"k":0,"ix":10},"p":{"a":0,"k":[200,150,0],"ix":2},"a":{"a":0,"k":[600,450,0],"ix":1},"s":{"a":0,"k":[32,32,100],"ix":6}},"ao":0,"w":1200,"h":900,"ip":0,"op":240,"st":0,"bm":0}],"markers":[]}